Correct_TDS_Sami/__init__.py
Correct_TDS_Sami/constants.py
Correct_TDS_Sami/fitc.py
Correct_TDS_Sami/fitf.py
Correct_TDS_Sami/interface.py
Correct_TDS_Sami/opt.py
Correct_TDS_Sami-0.1.1.dist-info/METADATA
Correct_TDS_Sami-0.1.1.dist-info/WHEEL
Correct_TDS_Sami-0.1.1.dist-info/top_level.txt
Correct_TDS_Sami-0.1.1.dist-info/RECORD
